auto_scailer/__init__.py
auto_scailer/auto_scailer.py
auto_scailer/plot.py
auto_scailer/utils.py
auto_scailer/config/config.ini
auto_scailer-2.1.0.dist-info/METADATA
auto_scailer-2.1.0.dist-info/WHEEL
auto_scailer-2.1.0.dist-info/entry_points.txt
auto_scailer-2.1.0.dist-info/top_level.txt
auto_scailer-2.1.0.dist-info/RECORD
