Metadata-Version: 2.1
Name: auto_scailer
Version: 2.1.0
Summary: config.ini에 설정된 값에 따라 container의 수를 자동적으로 증감하는 프로그램으로, 원할한 시스템 운영에 기여합니다.
Author-email: Mingk42 <xoals123456t@gmail.com>
License: MIT
Requires-Python: >=3.11
Requires-Dist: requests>=2.32.3
Requires-Dist: tz-kst>=0.5.2
Requires-Dist: pandas>=2.2.3
Requires-Dist: plotext>=5.3.2
